EventRecorder-1.0.0.data/scripts/remind
scripts/__init__.py
scripts/filterSearch.py
scripts/main.py
scripts/pickling.py
EventRecorder-1.0.0.dist-info/LICENSE.txt
EventRecorder-1.0.0.dist-info/METADATA
EventRecorder-1.0.0.dist-info/WHEEL
EventRecorder-1.0.0.dist-info/top_level.txt
EventRecorder-1.0.0.dist-info/RECORD
